Metadata-Version: 2.1
Name: readyapi-slim
Version: 0.110.3
Summary: ReadyAPI framework, high performance, easy to learn, fast to code, ready for production
Author-Email: KhulnaSoft DevOps <info@khulnasoft.com>
Classifier: Intended Audience :: Information Technology
Classifier: Intended Audience :: System Administrators
Classifier: Operating System :: OS Independent
Classifier: Programming Language :: Python :: 3
Classifier: Programming Language :: Python
Classifier: Topic :: Internet
Classifier: Topic :: Software Development :: Libraries :: Application Frameworks
Classifier: Topic :: Software Development :: Libraries :: Python Modules
Classifier: Topic :: Software Development :: Libraries
Classifier: Topic :: Software Development
Classifier: Typing :: Typed
Classifier: Development Status :: 4 - Beta
Classifier: Environment :: Web Environment
Classifier: Framework :: AsyncIO
Classifier: Framework :: Pydantic
Classifier: Framework :: Pydantic :: 1
Classifier: Intended Audience :: Developers
Classifier: License :: OSI Approved :: MIT License
Classifier: Programming Language :: Python :: 3 :: Only
Classifier: Programming Language :: Python :: 3.8
Classifier: Programming Language :: Python :: 3.9
Classifier: Programming Language :: Python :: 3.10
Classifier: Programming Language :: Python :: 3.11
Classifier: Programming Language :: Python :: 3.12
Classifier: Topic :: Internet :: WWW/HTTP :: HTTP Servers
Classifier: Topic :: Internet :: WWW/HTTP
Project-URL: Homepage, https://github.com/khulnasoft/readyapi
Project-URL: Documentation, https://readyapi.khulnasoft.com/
Project-URL: Repository, https://github.com/khulnasoft/readyapi
Requires-Python: >=3.8
Requires-Dist: starlette<0.38.0,>=0.37.2
Requires-Dist: pydantic!=1.8,!=1.8.1,!=2.0.0,!=2.0.1,!=2.1.0,<3.0.0,>=1.7.4
Requires-Dist: typing-extensions>=4.8.0
Requires-Dist: httpx>=0.23.0; extra == "standard"
Requires-Dist: jinja2>=2.11.2; extra == "standard"
Requires-Dist: python-multipart>=0.0.7; extra == "standard"
Requires-Dist: ujson!=4.0.2,!=4.1.0,!=4.2.0,!=4.3.0,!=5.0.0,!=5.1.0,>=4.0.1; extra == "standard"
Requires-Dist: orjson>=3.2.1; extra == "standard"
Requires-Dist: email_validator>=2.0.0; extra == "standard"
Requires-Dist: uvicorn[standard]>=0.12.0; extra == "standard"
Requires-Dist: httpx>=0.23.0; extra == "all"
Requires-Dist: jinja2>=2.11.2; extra == "all"
Requires-Dist: python-multipart>=0.0.7; extra == "all"
Requires-Dist: itsdangerous>=1.1.0; extra == "all"
Requires-Dist: pyyaml>=5.3.1; extra == "all"
Requires-Dist: ujson!=4.0.2,!=4.1.0,!=4.2.0,!=4.3.0,!=5.0.0,!=5.1.0,>=4.0.1; extra == "all"
Requires-Dist: orjson>=3.2.1; extra == "all"
Requires-Dist: email_validator>=2.0.0; extra == "all"
Requires-Dist: uvicorn[standard]>=0.12.0; extra == "all"
Requires-Dist: pydantic-settings>=2.0.0; extra == "all"
Requires-Dist: pydantic-extra-types>=2.0.0; extra == "all"
Provides-Extra: standard
Provides-Extra: all
